CONTRIBUTING.md
LICENSE
MANIFEST.in
README.rst
RELEASE_NOTES
setup.cfg
setup.py
easybuild/__init__.py
easybuild/easyblocks/__init__.py
easybuild/easyblocks/0/__init__.py
easybuild/easyblocks/a/__init__.py
easybuild/easyblocks/a/abaqus.py
easybuild/easyblocks/a/adf.py
easybuild/easyblocks/a/advisor.py
easybuild/easyblocks/a/aedt.py
easybuild/easyblocks/a/amber.py
easybuild/easyblocks/a/anaconda.py
easybuild/easyblocks/a/ansys.py
easybuild/easyblocks/a/ant.py
easybuild/easyblocks/a/aocc.py
easybuild/easyblocks/a/aomp.py
easybuild/easyblocks/a/armadillo.py
easybuild/easyblocks/b/__init__.py
easybuild/easyblocks/b/bazel.py
easybuild/easyblocks/b/berkeleygw.py
easybuild/easyblocks/b/binutils.py
easybuild/easyblocks/b/blat.py
easybuild/easyblocks/b/blis.py
easybuild/easyblocks/b/boost.py
easybuild/easyblocks/b/bowtie.py
easybuild/easyblocks/b/bowtie2.py
easybuild/easyblocks/b/bwa.py
easybuild/easyblocks/b/bzip2.py
easybuild/easyblocks/c/__init__.py
easybuild/easyblocks/c/cblas.py
easybuild/easyblocks/c/cgal.py
easybuild/easyblocks/c/chimera.py
easybuild/easyblocks/c/clang.py
easybuild/easyblocks/c/clang_aomp.py
easybuild/easyblocks/c/cmake.py
easybuild/easyblocks/c/code_server.py
easybuild/easyblocks/c/comsol.py
easybuild/easyblocks/c/cp2k.py
easybuild/easyblocks/c/cplex.py
easybuild/easyblocks/c/crispr_dav.py
easybuild/easyblocks/c/cryptography.py
easybuild/easyblocks/c/cuda.py
easybuild/easyblocks/c/cudacompat.py
easybuild/easyblocks/c/cudnn.py
easybuild/easyblocks/c/cufflinks.py
easybuild/easyblocks/d/__init__.py
easybuild/easyblocks/d/db.py
easybuild/easyblocks/d/dm_reverb.py
easybuild/easyblocks/d/dualsphysics.py
easybuild/easyblocks/e/__init__.py
easybuild/easyblocks/e/easybuildmeta.py
easybuild/easyblocks/e/eigen.py
easybuild/easyblocks/e/elpa.py
easybuild/easyblocks/e/elsi.py
easybuild/easyblocks/e/esmf.py
easybuild/easyblocks/e/extrae.py
easybuild/easyblocks/f/__init__.py
easybuild/easyblocks/f/faststructure.py
easybuild/easyblocks/f/fdtd_solutions.py
easybuild_easyblocks.egg-info/PKG-INFO
easybuild_easyblocks.egg-info/SOURCES.txt
easybuild_easyblocks.egg-info/dependency_links.txt
easybuild_easyblocks.egg-info/top_level.txt