Metadata-Version: 2.4
Name: easybuild-easyblocks
Version: 5.1.2
Summary: Python modules which implement support for installing particular  (groups of) software packages with EasyBuild.
Home-page: https://easybuild.io
Author: EasyBuild community
Author-email: easybuild@lists.ugent.be
License: GPLv2
Keywords: software build building installation installing compilation HPC scientific
Platform: Linux
Classifier: Development Status :: 5 - Production/Stable
Classifier: Environment :: Console
Classifier: Intended Audience :: System Administrators
Classifier: Operating System :: POSIX :: Linux
Classifier: Programming Language :: Python :: 3.6
Classifier: Programming Language :: Python :: 3.7
Classifier: Programming Language :: Python :: 3.8
Classifier: Programming Language :: Python :: 3.9
Classifier: Programming Language :: Python :: 3.10
Classifier: Programming Language :: Python :: 3.11
Classifier: Programming Language :: Python :: 3.12
Classifier: Programming Language :: Python :: 3.13
Classifier: Topic :: Software Development :: Build Tools
Requires: easybuild_framework(>=5.0)
License-File: LICENSE
Dynamic: author
Dynamic: author-email
Dynamic: classifier
Dynamic: description
Dynamic: home-page
Dynamic: keywords
Dynamic: license
Dynamic: license-file
Dynamic: platform
Dynamic: requires
Dynamic: summary
